httptime/__init__.py
httptime/core.py
httptime-0.1.0.dist-info/LICENSE
httptime-0.1.0.dist-info/METADATA
httptime-0.1.0.dist-info/WHEEL
httptime-0.1.0.dist-info/top_level.txt
httptime-0.1.0.dist-info/RECORD
