Metadata-Version: 2.1
Name: httptime
Version: 0.1.0
Summary: Module for timing http queries inside a python program.
Home-page: https://github.com/kkrizka/httptime
Author: Karol Krizka
Author-email: kkrizka@gmail.com
License: UNKNOWN
Platform: UNKNOWN
